kiarina/i18n/__init__.py
kiarina/i18n/_settings.py
kiarina/i18n/py.typed
kiarina/i18n/_helpers/__init__.py
kiarina/i18n/_helpers/get_i18n.py
kiarina/i18n/_helpers/get_system_language.py
kiarina/i18n/_helpers/get_translator.py
kiarina/i18n/_models/__init__.py
kiarina/i18n/_models/i18n.py
kiarina/i18n/_models/translator.py
kiarina/i18n/_operations/__init__.py
kiarina/i18n/_services/__init__.py
kiarina/i18n/_services/catalog.py
kiarina/i18n/_types/__init__.py
kiarina/i18n/_types/i18n_key.py
kiarina/i18n/_types/i18n_scope.py
kiarina/i18n/_types/language.py
kiarina/i18n_pydantic/__init__.py
kiarina/i18n_pydantic/py.typed
kiarina/i18n_pydantic/_helpers/__init__.py
kiarina/i18n_pydantic/_helpers/translate_pydantic_model.py
kiarina_i18n-1.35.0.dist-info/METADATA
kiarina_i18n-1.35.0.dist-info/WHEEL
kiarina_i18n-1.35.0.dist-info/RECORD
