Metadata-Version: 2.4
Name: kiarina-i18n
Version: 1.35.0
Summary: Simple internationalization (i18n) utilities for Python applications
Project-URL: Homepage, https://github.com/kiarina/kiarina-python
Project-URL: Repository, https://github.com/kiarina/kiarina-python
Project-URL: Issues, https://github.com/kiarina/kiarina-python/issues
Author-email: kiarina <kiarinadawa@gmail.com>
Maintainer-email: kiarina <kiarinadawa@gmail.com>
License-Expression: MIT
Keywords: i18n,internationalization,localization,translation
Classifier: Development Status :: 3 - Alpha
Classifier: Intended Audience :: Developers
Classifier: License :: OSI Approved :: MIT License
Classifier: Programming Language :: Python :: 3
Classifier: Programming Language :: Python :: 3.12
Classifier: Programming Language :: Python :: 3.13
Classifier: Topic :: Software Development :: Internationalization
Classifier: Topic :: Software Development :: Localization
Requires-Python: >=3.12
Requires-Dist: pydantic-settings-manager>=2.3.0
Requires-Dist: pydantic-settings>=2.0.0
Requires-Dist: pydantic>=2.0.0
Requires-Dist: pyyaml>=6.0.0
